Robinhood/Robinhood.py
Robinhood/__init__.py
Robinhood/endpoints.py
Robinhood/exceptions.py
Robinhood/trade_history_downloader.py
collegroup_rh-1.0.1.data/data/docs/example.py
collegroup_rh-1.0.1.data/data/docs/testing.md
collegroup_rh-1.0.1.data/data/tests/conftest.py
collegroup_rh-1.0.1.data/data/tests/helpers.py
collegroup_rh-1.0.1.data/data/tests/test_config.cfg
collegroup_rh-1.0.1.data/data/tests/test_getdata.py
collegroup_rh-1.0.1.data/data/tests/test_portfolio.py
collegroup_rh-1.0.1.dist-info/LICENSE
collegroup_rh-1.0.1.dist-info/METADATA
collegroup_rh-1.0.1.dist-info/WHEEL
collegroup_rh-1.0.1.dist-info/top_level.txt
collegroup_rh-1.0.1.dist-info/RECORD
